<includes>
	<include name="ViewPanelVideo">
		<control type="group">
			<posx>115</posx>
			<posy>60</posy>	
			<width>1120</width>
			<height>624</height>			
			<include>WindowOpenCloseZoomInOut</include>
			<visible>Control.IsVisible(50)</visible>
			<control type="image">
				<posx>-2</posx>
				<posy>-2</posy>
				<width>1124</width>
				<height>628</height>
				<texture>white.png</texture>
				<colordiffuse>10FFFFFF</colordiffuse>
			</control>
			<control type="panel" id="50">
				<posx>0</posx>
				<posy>0</posy>
				<width>1120</width>
				<height>624</height>
				<viewtype label="21371">icon</viewtype>
				<pagecontrol>60</pagecontrol>
				<scrolltime>200</scrolltime>
				<preloaditems>4</preloaditems>
				<onleft>1000</onleft>
				<onright>50</onright>
				<onup>9000</onup>
				<ondown>60</ondown>
				<orientation>horizontal</orientation>
				<itemlayout width="140" height="208">
					<control type="image">
						<posx>0</posx>
						<posy>0</posy>
						<width>140</width>
						<height>208</height>
						<texture background="true">$INFO[ListItem.Icon]</texture>
						<aspectratio scalediffuse="false">stretch</aspectratio>
					</control>
				</itemlayout>
				<focusedlayout width="148" height="208" condition="![Container.Column(0) | Container.Column(7)] + Container.Row(1)">
					<control type="image">
						<posx>-4</posx>
						<posy>0</posy>
						<width>148</width>
						<height>208</height>
						<texture background="true">$INFO[ListItem.Icon]</texture>
						<aspectratio scalediffuse="false">stretch</aspectratio>
						<bordertexture border="24">thumb-back.png</bordertexture>
						<bordersize>14</bordersize>
						<animation type="Focus" reversible="false">
							<effect type="zoom" start="116" end="140" center="auto" time="300" tween="back" easing="out"/>
						</animation>
					</control>
					<control type="image">
						<posx>115</posx>
						<posy>190</posy>
						<width>30</width>
						<height>30</height>
						<texture>$INFO[ListItem.Overlay]</texture>
						<animation type="Focus" reversible="false">
							<effect type="zoom" start="116" end="140" center="auto" time="300" tween="back" easing="out"/>
						</animation>
					</control>
				</focusedlayout>
				<focusedlayout width="148" height="208" condition="Container.Column(0) + Container.Row(1)">
					<control type="image">
						<posx>-4</posx>
						<posy>0</posy>
						<width>148</width>
						<height>208</height>
						<texture background="true">$INFO[ListItem.Icon]</texture>
						<aspectratio scalediffuse="false">stretch</aspectratio>
						<bordertexture border="24">thumb-back.png</bordertexture>
						<bordersize>14</bordersize>
						<animation type="Focus" reversible="false">
							<effect type="zoom" start="116" end="140" center="auto" time="300" tween="back" easing="out"/>
							<effect type="slide" start="0,0" end="10,0" time="300" tween="back" easing="out"/>
						</animation>
					</control>
					<control type="image">
						<posx>115</posx>
						<posy>190</posy>
						<width>30</width>
						<height>30</height>
						<texture>$INFO[ListItem.Overlay]</texture>
						<animation type="Focus" reversible="false">
							<effect type="zoom" start="116" end="140" center="auto" time="300" tween="back" easing="out"/>
							<effect type="slide" start="0,0" end="10,0" time="300" tween="back" easing="out"/>
						</animation>
					</control>
				</focusedlayout>
				<focusedlayout width="148" height="208" condition="![Container.Column(0) | Container.Column(7)] + Container.Row(0)">
					<control type="image">
						<posx>-4</posx>
						<posy>0</posy>
						<width>148</width>
						<height>208</height>
						<texture background="true">$INFO[ListItem.Icon]</texture>
						<aspectratio scalediffuse="false">stretch</aspectratio>
						<bordertexture border="24">thumb-back.png</bordertexture>
						<bordersize>14</bordersize>
						<animation type="Focus" reversible="false">
							<effect type="zoom" start="116" end="140" center="auto" time="300" tween="back" easing="out"/>
							<effect type="slide" start="0,0" end="0,16" time="300" tween="back" easing="out"/>
						</animation>
					</control>
					<control type="image">
						<posx>115</posx>
						<posy>190</posy>
						<width>30</width>
						<height>30</height>
						<texture>$INFO[ListItem.Overlay]</texture>
						<animation type="Focus" reversible="false">
							<effect type="zoom" start="116" end="140" center="auto" time="300" tween="back" easing="out"/>
							<effect type="slide" start="0,0" end="0,16" time="300" tween="back" easing="out"/>
						</animation>
					</control>
				</focusedlayout>
				<focusedlayout width="148" height="208" condition="Container.Column(7) + Container.Row(1)">
					<control type="image">
						<posx>-4</posx>
						<posy>0</posy>
						<width>148</width>
						<height>208</height>
						<texture background="true">$INFO[ListItem.Icon]</texture>
						<aspectratio scalediffuse="false">stretch</aspectratio>
						<bordertexture border="24">thumb-back.png</bordertexture>
						<bordersize>14</bordersize>
						<animation type="Focus" reversible="false">
							<effect type="zoom" start="116" end="140" center="auto" time="300" tween="back" easing="out"/>
							<effect type="slide" start="0,0" end="-10,0" time="300" tween="back" easing="out"/>
						</animation>
					</control>
					<control type="image">
						<posx>115</posx>
						<posy>190</posy>
						<width>30</width>
						<height>30</height>
						<texture>$INFO[ListItem.Overlay]</texture>
						<animation type="Focus" reversible="false">
							<effect type="zoom" start="116" end="140" center="auto" time="300" tween="back" easing="out"/>
							<effect type="slide" start="0,0" end="-10,0" time="300" tween="back" easing="out"/>
						</animation>
					</control>
				</focusedlayout>
				<focusedlayout width="148" height="208" condition="![Container.Column(0) | Container.Column(7)] + Container.Row(2)">
					<control type="image">
						<posx>-4</posx>
						<posy>0</posy>
						<width>148</width>
						<height>208</height>
						<texture background="true">$INFO[ListItem.Icon]</texture>
						<aspectratio scalediffuse="false">stretch</aspectratio>
						<bordertexture border="24">thumb-back.png</bordertexture>
						<bordersize>14</bordersize>
						<animation type="Focus" reversible="false">
							<effect type="zoom" start="116" end="140" center="auto" time="300" tween="back" easing="out"/>
							<effect type="slide" start="0,0" end="0,-16" time="300" tween="back" easing="out"/>
						</animation>
					</control>
					<control type="image">
						<posx>115</posx>
						<posy>190</posy>
						<width>30</width>
						<height>30</height>
						<texture>$INFO[ListItem.Overlay]</texture>
						<animation type="Focus" reversible="false">
							<effect type="zoom" start="116" end="140" center="auto" time="300" tween="back" easing="out"/>
							<effect type="slide" start="0,0" end="0,-16" time="300" tween="back" easing="out"/>
						</animation>
					</control>
				</focusedlayout>
				<focusedlayout width="148" height="208" condition="Container.Column(0) + Container.Row(0)">
					<control type="image">
						<posx>-4</posx>
						<posy>0</posy>
						<width>148</width>
						<height>208</height>
						<texture background="true">$INFO[ListItem.Icon]</texture>
						<aspectratio scalediffuse="false">stretch</aspectratio>
						<bordertexture border="24">thumb-back.png</bordertexture>
						<bordersize>14</bordersize>
						<animation type="Focus" reversible="false">
							<effect type="zoom" start="116" end="140" center="auto" time="300" tween="back" easing="out"/>
							<effect type="slide" start="0,0" end="10,16" time="300" tween="back" easing="out"/>
						</animation>
					</control>
					<control type="image">
						<posx>115</posx>
						<posy>190</posy>
						<width>30</width>
						<height>30</height>
						<texture>$INFO[ListItem.Overlay]</texture>
						<animation type="Focus" reversible="false">
							<effect type="zoom" start="116" end="140" center="auto" time="300" tween="back" easing="out"/>
							<effect type="slide" start="0,0" end="10,16" time="300" tween="back" easing="out"/>
						</animation>
					</control>
				</focusedlayout>
				<focusedlayout width="148" height="208" condition="Container.Column(7) + Container.Row(0)">
					<control type="image">
						<posx>-4</posx>
						<posy>0</posy>
						<width>148</width>
						<height>208</height>
						<texture background="true">$INFO[ListItem.Icon]</texture>
						<aspectratio scalediffuse="false">stretch</aspectratio>
						<bordertexture border="24">thumb-back.png</bordertexture>
						<bordersize>14</bordersize>
						<animation type="Focus" reversible="false">
							<effect type="zoom" start="116" end="140" center="auto" time="300" tween="back" easing="out"/>
							<effect type="slide" start="0,0" end="-10,16" time="300" tween="back" easing="out"/>
						</animation>
					</control>
					<control type="image">
						<posx>115</posx>
						<posy>190</posy>
						<width>30</width>
						<height>30</height>
						<texture>$INFO[ListItem.Overlay]</texture>
						<animation type="Focus" reversible="false">
							<effect type="zoom" start="116" end="140" center="auto" time="300" tween="back" easing="out"/>
							<effect type="slide" start="0,0" end="-10,16" time="300" tween="back" easing="out"/>
						</animation>
					</control>
				</focusedlayout>
				<focusedlayout width="148" height="208" condition="Container.Column(7) + Container.Row(2)">
					<control type="image">
						<posx>-4</posx>
						<posy>0</posy>
						<width>148</width>
						<height>208</height>
						<texture background="true">$INFO[ListItem.Icon]</texture>
						<aspectratio scalediffuse="false">stretch</aspectratio>
						<bordertexture border="24">thumb-back.png</bordertexture>
						<bordersize>14</bordersize>
						<animation type="Focus" reversible="false">
							<effect type="zoom" start="116" end="140" center="auto" time="300" tween="back" easing="out"/>
							<effect type="slide" start="0,0" end="-10,-16" time="300" tween="back" easing="out"/>
						</animation>
					</control>
					<control type="image">
						<posx>115</posx>
						<posy>190</posy>
						<width>30</width>
						<height>30</height>
						<texture>$INFO[ListItem.Overlay]</texture>
						<animation type="Focus" reversible="false">
							<effect type="zoom" start="116" end="140" center="auto" time="300" tween="back" easing="out"/>
							<effect type="slide" start="0,0" end="-10,-16" time="300" tween="back" easing="out"/>
						</animation>
					</control>
				</focusedlayout>
				<focusedlayout width="148" height="208" condition="Container.Column(0) + Container.Row(2)">
					<control type="image">
						<posx>-4</posx>
						<posy>0</posy>
						<width>148</width>
						<height>208</height>
						<texture background="true">$INFO[ListItem.Icon]</texture>
						<aspectratio scalediffuse="false">stretch</aspectratio>
						<bordertexture border="24">thumb-back.png</bordertexture>
						<bordersize>14</bordersize>
						<animation type="Focus" reversible="false">
							<effect type="zoom" start="116" end="140" center="auto" time="300" tween="back" easing="out"/>
							<effect type="slide" start="0,0" end="10,-16" time="300" tween="back" easing="out"/>
						</animation>
					</control>
					<control type="image">
						<posx>115</posx>
						<posy>190</posy>
						<width>30</width>
						<height>30</height>
						<texture>$INFO[ListItem.Overlay]</texture>
						<animation type="Focus" reversible="false">
							<effect type="zoom" start="116" end="140" center="auto" time="300" tween="back" easing="out"/>
							<effect type="slide" start="0,0" end="10,-16" time="300" tween="back" easing="out"/>
						</animation>
					</control>
				</focusedlayout>
			</control>
		</control>
		<control type="scrollbar" id="60">
			<posx>115</posx>
			<posy>685</posy>
			<width>1120</width>
			<height>20</height>
			<texturesliderbackground border="10,0,10,0">scrollbar_back.png</texturesliderbackground>
			<texturesliderbar>-</texturesliderbar>
			<texturesliderbarfocus>-</texturesliderbarfocus>
			<textureslidernib>scrollbar_nib.png_NF</textureslidernib>
			<textureslidernibfocus>scrollbar_nib_FO.png</textureslidernibfocus>
			<onup>50</onup>
			<ondown>50</ondown>
			<showonepage>false</showonepage>
			<orientation>horizontal</orientation>
			<include>VisibleFade</include>
			<visible allowhiddenfocus="true">Control.IsVisible(50) + Control.HasFocus(60)</visible>
		</control>
		<control type="group">
			<posx>103</posx>
			<posy>600</posy>
			<width>1177</width>
			<height>110</height>
			<animation effect="slide" start="0,120" end="0,0" time="300">Visible</animation>
			<animation effect="slide" start="0,0" end="0,120" time="300">Hidden</animation>
			<visible>Control.IsVisible(50) + Control.HasFocus(50) + !IsEmpty(ListItem.Title) + System.IdleTime(2)</visible>
			<control type="image">
				<posx>0</posx>
				<posy>0</posy>
				<width>1177</width>
				<height>120</height>
				<texture border="0,4,0,0">info_background.png</texture>
			</control>
			<control type="image">
				<posx>10</posx>
				<posy>25</posy>
				<width>64</width>
				<height>48</height>
				<texture fallback="mediaicon-resolution.png">mediaicons/resolution/$INFO[ListItem.VideoResolution,,.png]</texture>
				<colordiffuse>light</colordiffuse>
			</control>
			<control type="image">
				<posx>70</posx>
				<posy>25</posy>
				<width>64</width>
				<height>48</height>
				<texture fallback="mediaicon-aspectratio.png">mediaicons/aspectratio/$INFO[ListItem.VideoAspect,,.png]</texture>
				<colordiffuse>light</colordiffuse>
			</control>
			<control type="image">
				<posx>10</posx>
				<posy>70</posy>
				<width>64</width>
				<height>48</height>
				<texture fallback="mediaicon-videocodec.png">mediaicons/videocodec/$INFO[ListItem.VideoCodec,,.png]</texture>
				<colordiffuse>light</colordiffuse>
			</control>
			<control type="image">
				<posx>70</posx>
				<posy>70</posy>
				<width>64</width>
				<height>48</height>
				<texture fallback="mediaicon-audiocodec.png">$VAR[MediaIconAudioCodec]</texture>
				<colordiffuse>light</colordiffuse>
			</control>
			<control type="image">
				<posx>140</posx>
				<posy>35</posy>
				<width>1</width>
				<height>75</height>
				<texture>white.png</texture>
				<colordiffuse>60FFFFFF</colordiffuse>
			</control>
			<control type="label">
				<posx>140</posx>
				<posy>30</posy>
				<width>900</width>
				<height>30</height>
				<label>[B]$INFO[ListItem.Title][/B]</label>
				<align>center</align>
				<font>font28</font>
				<textcolor>white</textcolor>
			</control>
			<control type="image">
				<posx>190</posx>
				<posy>64</posy>
				<width>800</width>
				<height>1</height>
				<texture>white.png</texture>
				<colordiffuse>60FFFFFF</colordiffuse>				
			</control>
			<control type="label">
				<posx>280</posx>
				<posy>68</posy>
				<width>140</width>
				<height>30</height>
				<label>Director:</label>
				<align>right</align>
				<font>font17m</font>
				<textcolor>normal</textcolor>
			</control>
			<control type="label">
				<posx>285</posx>
				<posy>68</posy>
				<width>300</width>
				<height>30</height>
				<label>$INFO[ListItem.Director]</label>
				<font>font18</font>
				<textcolor>light</textcolor>
			</control>
			<control type="label">
				<posx>280</posx>
				<posy>88</posy>
				<width>140</width>
				<height>30</height>
				<label>Genre:</label>
				<align>right</align>
				<font>font17m</font>
				<textcolor>normal</textcolor>
			</control>
			<control type="label">
				<posx>285</posx>
				<posy>88</posy>
				<width>300</width>
				<height>30</height>
				<label>$INFO[ListItem.Genre]</label>
				<font>font18</font>
				<textcolor>light</textcolor>
			</control>
			<control type="label">
				<posx>730</posx>
				<posy>68</posy>
				<width>140</width>
				<height>30</height>
				<label>Studio:</label>
				<align>right</align>
				<font>font17m</font>
				<textcolor>normal</textcolor>
			</control>
			<control type="label">
				<posx>735</posx>
				<posy>68</posy>
				<width>300</width>
				<height>30</height>
				<label>$INFO[ListItem.Studio]</label>
				<font>font18</font>
				<textcolor>light</textcolor>
			</control>
			<control type="label">
				<posx>730</posx>
				<posy>88</posy>
				<width>140</width>
				<height>30</height>
				<label>Duration:</label>
				<align>right</align>
				<font>font17m</font>
				<textcolor>normal</textcolor>
			</control>
			<control type="label">
				<posx>735</posx>
				<posy>88</posy>
				<width>300</width>
				<height>30</height>
				<label>$INFO[ListItem.Duration] Minutes</label>
				<font>font18</font>
				<textcolor>light</textcolor>
			</control>
			<control type="image">
				<posx>1040</posx>
				<posy>35</posy>
				<width>1</width>
				<height>75</height>
				<texture>white.png</texture>
				<colordiffuse>60FFFFFF</colordiffuse>				
			</control>
			<control type="label">
				<posx>1043</posx>
				<posy>30</posy>
				<width>125</width>
				<height>30</height>
				<label>[B]$INFO[ListItem.Year][/B]</label>
				<align>center</align>
				<font>font30m</font>
				<textcolor>normal</textcolor>
			</control>
			<control type="label">
				<posx>1105</posx>
				<posy>85</posy>
				<width>60</width>
				<height>20</height>
				<label>rating</label>
				<font>font16</font>
				<textcolor>light</textcolor>
				<align>right</align>
			</control>
			<control type="label">
				<posx>1110</posx>
				<posy>74</posy>
				<width>70</width>
				<height>40</height>
				<label>[B]$INFO[ListItem.Rating][/B]</label>
				<font>font24m</font>
				<textcolor>light</textcolor>
			</control>
		</control>
	</include>
</includes>
